full_adder/full_adder.srcs/sources_1/new/full_adder.sv
`timescale 1ns / 1ps
//////////////////////////////////////////////////////////////////////////////////
// Company: 
// Engineer: 
// 
// Create Date: 09/08/2023 09:17:27 AM
// Design Name: 
// Module Name: full_adder
// Project Name: 
// Target Devices: 
// Tool Versions: 
// Description: 
// 
// Dependencies: 
// 
// Revision:
// Revision 0.01 - File Created
// Additional Comments:
// 
//////////////////////////////////////////////////////////////////////////////////


module full_adder  (
    input logic signed a,b,cin,
    output logic signed sum,co
);
logic wire1,wire2,wire3; 
assign wire1= a ^ b;
assign wire2 = wire1 & cin;
assign wire3 = a & b;

always_comb begin 
    sum= wire1 ^ cin;
    co = wire2 | wire3;    
end
    
endmodule

full_adder/full_adder.srcs/sources_1/new/full_adder_tb.sv
`timescale 1ns/1ps
module full_adder_tb ();// testbench doesnt have any ports // this is software not in hardware
// lets declare the variable of the uut (unit under test) port.
logic a=0,b=0,cin=0,sum,co;

// lets instantiate the dut
//full_adder uut(a,b,cin,sum,cout); // method 1
full_adder dut(.*);                 // method 2. preferred method

// lets start the simulation
initial begin
    // 1st dump the waveform.
    $dumpfile("full_adder.vcd"); $dumpvars(0,dut);
   #30 a = 1; b = 0; cin = 0; // Test case 1
    #10 a = 0; b = 0; cin = 1; // Test case 2
    #20 a = 1; b = 1; cin = 0; // Test case 3
    #10 a = 1; b = 0; cin = 0; // Test case 4
    #10 a = 0; b = 1; cin = 0; // Test case 5
    #10 a = 0; b = 0; cin = 1; // Test case 6
    #10 a = 1; b = 1; cin = 1; // Test case 7
    #10 a = 1; b = 0; cin = 1; // Test case 8
    #10 a = 0; b = 1; cin = 1; // Test case 9
    #10 a = 1; b = 1; cin = 0; // Test case 10

    // assert calculates the output and compares with the expected output.
    assert ({co,sum}==a+b+cin)
            $display("ok");  // if ok then display ok   
    else   $error("error"); // if not ok then display error

    #10 a <= 1; b <= 1; cin <= 1;
    #1 assert (dut.wire1 == 0)  // here we can check the internal wires also.
    else   $error("false.wire1: %d",dut.wire1); // here %d is used to display the value of the wire1 (string formating)
    $finish; // this is used to stop the simulation
end


    
endmodule

full_adder/full_adder.sim/sim_1/behav/xsim/full_adder.vcd
$date
   Fri Sep  8 09:52:37 2023
$end
$version
  2023.1
$end
$timescale
  1ps
$end
$scope module full_adder_tb $end
$scope module dut $end
$var wire 1 ! a $end
$var wire 1 " b $end
$var wire 1 # cin $end
$var reg 1 $ sum $end
$var reg 1 % co $end
$var reg 1 & wire1 $end
$var reg 1 ' wire2 $end
$var reg 1 ( wire3 $end
$upscope $end
$upscope $end
$enddefinitions $end
#0
$dumpvars
0!
0"
0#
0$
0%
0&
0'
0(
$end
#30000
1!
1$
1&
#40000
0!
1#
0&
0'
#60000
1!
1"
0#
0$
1%
1(
#70000
0"
1$
0%
1&
0(
#80000
0!
1"
#90000
0"
1#
0&
0'
#100000
1!
1"
1%
1(
#110000
0"
0$
1&
1'
0(
#120000
0!
1"
#130000
1!
0#
0&
0'
1(
